setup.py
remote_auth/__init__.py
remote_auth/admin.py
remote_auth/apps.py
remote_auth/backends.py
remote_auth/middleware.py
remote_auth/models.py
remote_auth/session.py
remote_auth/settings.py
remote_auth/tests.py
remote_auth/views.py
remote_auth.egg-info/PKG-INFO
remote_auth.egg-info/SOURCES.txt
remote_auth.egg-info/dependency_links.txt
remote_auth.egg-info/not-zip-safe
remote_auth.egg-info/top_level.txt