Metadata-Version: 1.1
Name: remote-auth
Version: 0.0.6
Summary: Provide multiple Django Auth support to a project
Home-page: https://github.com/mymusise/django-remote-auth
Author: mymusise
Author-email: mymusise1@gmail.com
License: MIT
Keywords: remote multi default django auth
Platform: UNKNOWN
Classifier: Development Status :: 5 - Production/Stable
Classifier: Environment :: Web Environment
Classifier: Intended Audience :: Developers
Classifier: License :: OSI Approved :: MIT License
Classifier: Framework :: Django
Classifier: Programming Language :: Python
Classifier: Programming Language :: Python :: 3
Classifier: Topic :: Software Development
